<?xml version = '1.0' encoding = 'UTF-8'?>
<TableProxyOraclev10g class="oracle.dbtools.crest.model.design.storage.oracle.v10g.TableProxyOraclev10g" name="LETTER_ASSOC" id="49357FF4-7DEB-2C74-DD55-3E6340BC8B03" directorySegmentName="seg_0">
<createdBy>grantlewis</createdBy>
<createdTime>2012-06-26 22:59:45 UTC</createdTime>
<ownerDesignName>vbmsDB</ownerDesignName>
<logging>YES</logging>
<columnProxies>
<ColumnProxy class="oracle.dbtools.crest.model.design.storage.oracle.v10g.ColumnProxyOraclev10g" name="ID" id="25504E81-C057-1115-B054-AD2A5B958952">
<createdBy>grantlewis</createdBy>
<createdTime>2012-06-26 22:59:45 UTC</createdTime>
<ownerDesignName>vbmsDB</ownerDesignName>
</ColumnProxy>
<ColumnProxy class="oracle.dbtools.crest.model.design.storage.oracle.v10g.ColumnProxyOraclev10g" name="LASTUPDATEDT" id="43AD38D3-45D2-6644-4A35-660DE827D8F5">
<createdBy>grantlewis</createdBy>
<createdTime>2012-06-26 22:59:45 UTC</createdTime>
<ownerDesignName>vbmsDB</ownerDesignName>
<defaultValue>SYSDATE</defaultValue>
</ColumnProxy>
<ColumnProxy class="oracle.dbtools.crest.model.design.storage.oracle.v10g.ColumnProxyOraclev10g" name="EXPIRATIONDT" id="8E9484CE-AF07-E5CB-9545-6D9EE16A4CD9">
<createdBy>grantlewis</createdBy>
<createdTime>2012-06-26 22:59:45 UTC</createdTime>
<ownerDesignName>vbmsDB</ownerDesignName>
</ColumnProxy>
<ColumnProxy class="oracle.dbtools.crest.model.design.storage.oracle.v10g.ColumnProxyOraclev10g" name="ATTRIBUTE_ID" id="91D6C4D9-035C-3556-1298-C8D3D4E4AFF8">
<createdBy>grantlewis</createdBy>
<createdTime>2012-06-26 22:59:45 UTC</createdTime>
<ownerDesignName>vbmsDB</ownerDesignName>
</ColumnProxy>
<ColumnProxy class="oracle.dbtools.crest.model.design.storage.oracle.v10g.ColumnProxyOraclev10g" name="CREATEDT" id="CFBD0DA2-20D1-74F6-77BE-C2356215A31F">
<createdBy>grantlewis</createdBy>
<createdTime>2012-06-26 22:59:45 UTC</createdTime>
<ownerDesignName>vbmsDB</ownerDesignName>
<defaultValue>SYSDATE</defaultValue>
</ColumnProxy>
<ColumnProxy class="oracle.dbtools.crest.model.design.storage.oracle.v10g.ColumnProxyOraclev10g" name="VBMSUSERID" id="E83D1DC0-3319-DAF3-E7F0-B88A0ED96222">
<createdBy>grantlewis</createdBy>
<createdTime>2012-06-26 22:59:45 UTC</createdTime>
<ownerDesignName>vbmsDB</ownerDesignName>
</ColumnProxy>
<ColumnProxy class="oracle.dbtools.crest.model.design.storage.oracle.v10g.ColumnProxyOraclev10g" name="LETTER_ID" id="EFE6DDFE-B795-8307-9CE5-04A85B95681C">
<createdBy>grantlewis</createdBy>
<createdTime>2012-06-26 22:59:45 UTC</createdTime>
<ownerDesignName>vbmsDB</ownerDesignName>
</ColumnProxy>
<ColumnProxy class="oracle.dbtools.crest.model.design.storage.oracle.v10g.ColumnProxyOraclev10g" name="ATTRIBUTE_CLASS" id="F440967D-1FFD-F765-D137-D751A604CE5B">
<createdBy>grantlewis</createdBy>
<createdTime>2012-06-26 22:59:45 UTC</createdTime>
<ownerDesignName>vbmsDB</ownerDesignName>
</ColumnProxy>
</columnProxies>
<indexProxies>
<IndexProxy class="oracle.dbtools.crest.model.design.storage.oracle.v10g.IndexProxyOraclev10g" name="LETTER_ASSOC_VU_IDX" id="78601518-0CA5-15C4-99AB-D891FBE33EE8">
<createdBy>grantlewis</createdBy>
<createdTime>2012-06-26 22:59:45 UTC</createdTime>
<ownerDesignName>vbmsDB</ownerDesignName>
<sortedRows>SORTED</sortedRows>
</IndexProxy>
<IndexProxy class="oracle.dbtools.crest.model.design.storage.oracle.v10g.IndexProxyOraclev10g" name="LETTER_ASSOC_L_IDX" id="EBC2AF20-093C-42B3-85D5-0AFF0C510069">
<createdBy>grantlewis</createdBy>
<createdTime>2012-06-26 22:59:45 UTC</createdTime>
<ownerDesignName>vbmsDB</ownerDesignName>
<sortedRows>SORTED</sortedRows>
</IndexProxy>
</indexProxies>
<foreignKeys>
<ForeignKey class="oracle.dbtools.crest.model.design.storage.oracle.v10g.FKProxyOraclev10g" name="LETTER_ASSOC_L_FK" id="99B1DE6E-0DA4-8578-D530-A115DF0D28F4">
<createdBy>grantlewis</createdBy>
<createdTime>2012-06-26 22:59:45 UTC</createdTime>
<ownerDesignName>vbmsDB</ownerDesignName>
</ForeignKey>
</foreignKeys>
<primaryKeys>
<PrimaryKey class="oracle.dbtools.crest.model.design.storage.oracle.v10g.PKProxyOraclev10g" name="LETTER_ASSOC_PK" id="41510EA0-D9C4-8C40-1E2E-779C2BA06CBD">
<createdBy>grantlewis</createdBy>
<createdTime>2012-06-26 22:59:45 UTC</createdTime>
<ownerDesignName>vbmsDB</ownerDesignName>
<sortedRows>SORTED</sortedRows>
<indexSort>SORTED</indexSort>
</PrimaryKey>
</primaryKeys>
</TableProxyOraclev10g>