<?xml version = '1.0' encoding = 'UTF-8'?>
<TableProxyOraclev11g class="oracle.dbtools.crest.model.design.storage.oracle.v11g.TableProxyOraclev11g" name="LETTER" id="14E867E5-4902-1242-5215-A2A105051C9D" directorySegmentName="seg_0">
<createdBy>grantlewis</createdBy>
<createdTime>2012-06-26 22:55:12 UTC</createdTime>
<ownerDesignName>vbmsDB</ownerDesignName>
<nameHasQuotes>true</nameHasQuotes>
<logging>YES</logging>
<segment>2FB3BB9F-BABE-EDF9-0A10-873FE71E6E75</segment>
<tableSpace>49AE25E2-B733-BD6F-38F5-F16733FDBE64</tableSpace>
<columnProxies>
<ColumnProxy class="oracle.dbtools.crest.model.design.storage.oracle.v11g.ColumnProxyOraclev11g" name="CREATEDT" id="01164979-6D4C-B892-350B-659487F370F2">
<createdBy>grantlewis</createdBy>
<createdTime>2012-06-26 22:55:12 UTC</createdTime>
<ownerDesignName>vbmsDB</ownerDesignName>
<defaultValue>SYSDATE</defaultValue>
</ColumnProxy>
<ColumnProxy class="oracle.dbtools.crest.model.design.storage.oracle.v11g.ColumnProxyOraclev11g" name="PROVIDER_NAME" id="03611D33-3477-B8C7-7676-79C91F092BC9">
<createdBy>grantlewis</createdBy>
<createdTime>2012-06-26 22:55:12 UTC</createdTime>
<ownerDesignName>vbmsDB</ownerDesignName>
</ColumnProxy>
<ColumnProxy class="oracle.dbtools.crest.model.design.storage.oracle.v11g.ColumnProxyOraclev11g" name="SENTDT" id="13CEBD35-DAAA-E3C1-EBA3-A58763968D5A">
<createdBy>grantlewis</createdBy>
<createdTime>2012-06-26 22:55:12 UTC</createdTime>
<ownerDesignName>vbmsDB</ownerDesignName>
</ColumnProxy>
<ColumnProxy class="oracle.dbtools.crest.model.design.storage.oracle.v11g.ColumnProxyOraclev11g" name="EXPIRATIONDT" id="25BEBBCB-186B-E634-B01D-BA9AE9D49A70">
<createdBy>grantlewis</createdBy>
<createdTime>2012-06-26 22:55:12 UTC</createdTime>
<ownerDesignName>vbmsDB</ownerDesignName>
</ColumnProxy>
<ColumnProxy class="oracle.dbtools.crest.model.design.storage.oracle.v11g.ColumnProxyOraclev11g" name="STATIONNUMBER" id="3F8814B9-7B28-CC1B-4518-CB413E5BCABB">
<createdBy>grantlewis</createdBy>
<createdTime>2012-06-26 22:55:12 UTC</createdTime>
<ownerDesignName>vbmsDB</ownerDesignName>
</ColumnProxy>
<ColumnProxy class="oracle.dbtools.crest.model.design.storage.oracle.v11g.ColumnProxyOraclev11g" name="LASTUPDATEDT" id="68ACA164-3404-420A-D074-79805D89B7BA">
<createdBy>grantlewis</createdBy>
<createdTime>2012-06-26 22:55:12 UTC</createdTime>
<ownerDesignName>vbmsDB</ownerDesignName>
<defaultValue>SYSDATE</defaultValue>
</ColumnProxy>
<ColumnProxy class="oracle.dbtools.crest.model.design.storage.oracle.v11g.ColumnProxyOraclev11g" name="LETTER_TYPE" id="7ECB48BF-77C4-1881-75C0-CA6FA86E6B13">
<createdBy>grantlewis</createdBy>
<createdTime>2012-06-26 22:55:12 UTC</createdTime>
<ownerDesignName>vbmsDB</ownerDesignName>
</ColumnProxy>
<ColumnProxy class="oracle.dbtools.crest.model.design.storage.oracle.v11g.ColumnProxyOraclev11g" name="REFER_TO_LINE" id="819537BB-7FA5-9FE6-362C-FD57A7C7C101">
<createdBy>grantlewis</createdBy>
<createdTime>2012-06-26 22:55:12 UTC</createdTime>
<ownerDesignName>vbmsDB</ownerDesignName>
</ColumnProxy>
<ColumnProxy class="oracle.dbtools.crest.model.design.storage.oracle.v11g.ColumnProxyOraclev11g" name="VBMSUSERID" id="8BC577FA-2E30-FC66-9924-25B786CD6AF1">
<createdBy>grantlewis</createdBy>
<createdTime>2012-06-26 22:55:12 UTC</createdTime>
<ownerDesignName>vbmsDB</ownerDesignName>
</ColumnProxy>
<ColumnProxy class="oracle.dbtools.crest.model.design.storage.oracle.v11g.ColumnProxyOraclev11g" name="DOCUMENT_TYPE_LU_ID" id="9CB9EC19-529B-D7F4-97EE-3F327DBE48C7">
<createdBy>grantlewis</createdBy>
<createdTime>2012-06-26 22:55:12 UTC</createdTime>
<ownerDesignName>vbmsDB</ownerDesignName>
</ColumnProxy>
<ColumnProxy class="oracle.dbtools.crest.model.design.storage.oracle.v11g.ColumnProxyOraclev11g" name="GENERATIONDT" id="C20A8ED9-09D0-1BE6-0785-071B7A7321AC">
<createdBy>grantlewis</createdBy>
<createdTime>2012-06-26 22:55:12 UTC</createdTime>
<ownerDesignName>vbmsDB</ownerDesignName>
</ColumnProxy>
<ColumnProxy class="oracle.dbtools.crest.model.design.storage.oracle.v11g.ColumnProxyOraclev11g" name="ID" id="CDD08F05-0EFD-4B49-A009-A20808E82C42">
<createdBy>grantlewis</createdBy>
<createdTime>2012-06-26 22:55:12 UTC</createdTime>
<ownerDesignName>vbmsDB</ownerDesignName>
</ColumnProxy>
<ColumnProxy class="oracle.dbtools.crest.model.design.storage.oracle.v11g.ColumnProxyOraclev11g" name="PROVIDER_ADDRESS_ID" id="CE920E39-F7F4-3934-722E-C6409CFD944D">
<createdBy>grantlewis</createdBy>
<createdTime>2012-06-26 22:55:12 UTC</createdTime>
<ownerDesignName>vbmsDB</ownerDesignName>
</ColumnProxy>
<ColumnProxy class="oracle.dbtools.crest.model.design.storage.oracle.v11g.ColumnProxyOraclev11g" name="CLAIM_ID" id="D2CFD3DB-B93B-7770-BA32-34D3624D4D63">
<createdBy>grantlewis</createdBy>
<createdTime>2012-06-26 22:55:12 UTC</createdTime>
<ownerDesignName>vbmsDB</ownerDesignName>
</ColumnProxy>
<ColumnProxy class="oracle.dbtools.crest.model.design.storage.oracle.v11g.ColumnProxyOraclev11g" name="UNIQUE_ID" id="D5FBFDBF-75CB-6192-A9B8-9D33D509B4ED">
<createdBy>grantlewis</createdBy>
<createdTime>2012-06-26 22:55:12 UTC</createdTime>
<ownerDesignName>vbmsDB</ownerDesignName>
</ColumnProxy>
<ColumnProxy class="oracle.dbtools.crest.model.design.storage.oracle.v11g.ColumnProxyOraclev11g" name="SALUTATION" id="E488FADE-DFF4-4338-D4BA-605C10E1E244">
<createdBy>grantlewis</createdBy>
<createdTime>2012-06-26 22:55:12 UTC</createdTime>
<ownerDesignName>vbmsDB</ownerDesignName>
</ColumnProxy>
</columnProxies>
<indexProxies>
<IndexProxy class="oracle.dbtools.crest.model.design.storage.oracle.v10g.IndexProxyOraclev10g" name="LETTER_CLAIM_IDX" id="4D37EFA2-5237-F9A9-9E7B-DCE925156753">
<createdBy>grantlewis</createdBy>
<createdTime>2012-06-26 22:55:12 UTC</createdTime>
<ownerDesignName>vbmsDB</ownerDesignName>
<computeStatistics>YES</computeStatistics>
<logging></logging>
<segment>1E963843-DFF4-D5A6-9D3D-7B61F3FBA448</segment>
<sortedRows>SORTED</sortedRows>
<tableSpace>49AE25E2-B733-BD6F-38F5-F16733FDBE64</tableSpace>
</IndexProxy>
<IndexProxy class="oracle.dbtools.crest.model.design.storage.oracle.v10g.IndexProxyOraclev10g" name="LETTER_VU_IDX" id="BCE16D7C-324C-CC34-4B6E-4D33671FFBCA">
<createdBy>grantlewis</createdBy>
<createdTime>2012-06-26 22:55:12 UTC</createdTime>
<ownerDesignName>vbmsDB</ownerDesignName>
<computeStatistics>YES</computeStatistics>
<logging></logging>
<segment>1E963843-DFF4-D5A6-9D3D-7B61F3FBA448</segment>
<sortedRows>SORTED</sortedRows>
<tableSpace>49AE25E2-B733-BD6F-38F5-F16733FDBE64</tableSpace>
</IndexProxy>
<IndexProxy class="oracle.dbtools.crest.model.design.storage.oracle.v10g.IndexProxyOraclev10g" name="LETTER_SN_IDX" id="CF5C4DF0-DF3E-5DD9-955D-7A0818E74612">
<createdBy>grantlewis</createdBy>
<createdTime>2012-06-26 22:55:12 UTC</createdTime>
<ownerDesignName>vbmsDB</ownerDesignName>
<computeStatistics>YES</computeStatistics>
<logging></logging>
<segment>1E963843-DFF4-D5A6-9D3D-7B61F3FBA448</segment>
<sortedRows>SORTED</sortedRows>
<tableSpace>49AE25E2-B733-BD6F-38F5-F16733FDBE64</tableSpace>
</IndexProxy>
</indexProxies>
<primaryKeys>
<PrimaryKey class="oracle.dbtools.crest.model.design.storage.oracle.v10g.PKProxyOraclev10g" name="LETTER_PK" id="37C0E480-9E3F-C367-FA68-3CAC024546DE">
<createdBy>grantlewis</createdBy>
<createdTime>2012-06-26 22:55:12 UTC</createdTime>
<ownerDesignName>vbmsDB</ownerDesignName>
<logging></logging>
<sortedRows>SORTED</sortedRows>
<tableSpace>49AE25E2-B733-BD6F-38F5-F16733FDBE64</tableSpace>
<indexSegment>57EE4F59-50EE-AE30-392E-911CB2F4BD64</indexSegment>
<indexSort>SORTED</indexSort>
<usingIndex>BY INDEX NAME</usingIndex>
<computeStatistics>YES</computeStatistics>
</PrimaryKey>
</primaryKeys>
</TableProxyOraclev11g>