<?xml version = '1.0' encoding = 'UTF-8'?>
<Relation class="oracle.dbtools.crest.model.design.logical.Relation" name="FILLINVALUESTOSTD_OUTPUT_ARGMT" id="770A36B0-5035-8026-B285-C309983A836F" directorySegmentName="seg_0">
<createdBy>grantlewis</createdBy>
<createdTime>2012-06-26 18:55:54 UTC</createdTime>
<ownerDesignName>vbmsDB</ownerDesignName>
<engineerTo>
<item key="5FBADF07-A54B-F85B-A18B-5F025C014498" value="true"/>
</engineerTo>
<identifying>false</identifying>
<optionalSource>true</optionalSource>
<optionalTarget>true</optionalTarget>
<sourceCardinality>1</sourceCardinality>
<sourceEntity>4E2F7815-6CDA-4FCE-1F59-F16347C50386</sourceEntity>
<targetCardinalityString>1</targetCardinalityString>
<targetEntity>E98DBFC6-052A-D44F-2313-5A751DE4450C</targetEntity>
<transferable>true</transferable>
</Relation>